vault_wrapper/__init__.py
vault_wrapper/client.py
vault_wrapper/policy.py
vault_wrapper-0.3.4.dist-info/LICENSE.md
vault_wrapper-0.3.4.dist-info/METADATA
vault_wrapper-0.3.4.dist-info/WHEEL
vault_wrapper-0.3.4.dist-info/top_level.txt
vault_wrapper-0.3.4.dist-info/RECORD
