Metadata-Version: 2.1
Name: vault-wrapper
Version: 0.3.4
Summary: Small hvac wrapper
Home-page: https://github.com/JoelLefkowitz/vault-wrapper
Author: Joel Lefkowitz
Author-email: joellefkowitz@hotmail.com
License: UNKNOWN
Keywords: vault
Platform: UNKNOWN
Classifier: License :: OSI Approved :: MIT License
Classifier: Programming Language :: Python :: 3.6
Classifier: Programming Language :: Python :: 3.7
Classifier: Programming Language :: Python :: 3.8
Requires-Python: >=3.6
Requires-Dist: hvac
Requires-Dist: retry
Requires-Dist: requests
Provides-Extra: dev
Requires-Dist: black ; extra == 'dev'
Requires-Dist: autoflake ; extra == 'dev'
Requires-Dist: isort ; extra == 'dev'
Requires-Dist: mypy ; extra == 'dev'
Requires-Dist: wheel ; extra == 'dev'
Provides-Extra: docs
Requires-Dist: sphinx ; extra == 'docs'
Requires-Dist: pyimport ; extra == 'docs'
Requires-Dist: pypandoc ; extra == 'docs'
Requires-Dist: sphinxcontrib.apidoc ; extra == 'docs'
Requires-Dist: sphinxcontrib.pandoc-markdown ; extra == 'docs'
Requires-Dist: sphinx-autodoc-annotation ; extra == 'docs'
Requires-Dist: yummy-sphinx-theme ; extra == 'docs'
Provides-Extra: tests
Requires-Dist: pytest ; extra == 'tests'
Requires-Dist: pytest-cov ; extra == 'tests'
Requires-Dist: pytest-html ; extra == 'tests'
Requires-Dist: pytest-sugar ; extra == 'tests'
Requires-Dist: pytest-bdd ; extra == 'tests'
Requires-Dist: pytest-watch ; extra == 'tests'
